README.rst
betamax_yaml_serializer.py
setup.py
betamax_yaml_serializer.egg-info/PKG-INFO
betamax_yaml_serializer.egg-info/SOURCES.txt
betamax_yaml_serializer.egg-info/dependency_links.txt
betamax_yaml_serializer.egg-info/top_level.txt