Metadata-Version: 1.1
Name: betamax-yaml-serializer
Version: 0.1.5
Summary: YAML serializer for betamax
Home-page: https://github.com/kragniz/betamax-yaml-serializer
Author: Louis Taylor
Author-email: louis@kragniz.eu
License: UNKNOWN
Platform: UNKNOWN
Classifier: Development Status :: 2 - Pre-Alpha
Classifier: Programming Language :: Python
Classifier: Programming Language :: Python :: 2
Classifier: Programming Language :: Python :: 2.7
Classifier: Programming Language :: Python :: 3
Classifier: Programming Language :: Python :: 3.4
Classifier: Programming Language :: Python :: 3.5
Requires: PyYAML
